<?xml version="1.0" encoding="utf-8"?>
<lng xmlns="http://energy.icis.com/ns/eu-gas-fundamentals" created-on="2016-03-28T10:30:39Z+1"><country>Spain</country><point>Sagunto</point><lso>Saggas</lso><gas-quality>H</gas-quality><plant-type>LNG Peak Shaving/LNG Terminal</plant-type><period type="gas-day" from="2012-11-17T23:00:00Z" to="2012-11-18T23:00:00Z"/><acquired>2016-03-28T10:30:39Z+1</acquired><state version="1">Provisional</state><capacity mwh="4099340.68937246" mcm="370.275165" cmlng="600000.0" tlng="270000.0" country-percentage="18.5356811862836%"/><stock-level mwh="1482280.96947935" mcm="133.88779691235" cmlng="216954.0" tlng="97629.300000000003" full="36.159%"/><unloaded-inflow mwh="881143.315781826" mcm="78.590286645975" cmlng="127349.0" tlng="57307.050000000003"/><send-out mwh="112687.013764213" mcm="10.099255125375" cmlng="16365.0" tlng="7364.25"/></lng>