<?xml version="1.0" encoding="utf-8"?>
<lng xmlns="http://energy.icis.com/ns/eu-gas-fundamentals" created-on="2017-08-21T10:10:36Z+1"><country>Spain</country><point>Huelva</point><lso>Enagas</lso><gas-quality>H</gas-quality><plant-type>LNG Peak Shaving/LNG Terminal</plant-type><period type="gas-day" from="2017-08-20T23:00:00Z+1" to="2017-08-21T23:00:00Z+1"/><acquired>2017-08-21T10:10:36Z+1</acquired><state version="31">Forecast</state><capacity mwh="4232569.26177706" mcm="382.3091078625" cmlng="619500.0" tlng="278775.0" country-percentage="18.6793306196291%"/><stock-level mwh="2053976.2172423" mcm="185.526512767568" cmlng="296855.02074937802" tlng="133584.75933722" full="48.5278820075336%"/><unloaded-inflow mwh="0" mcm="0" cmlng="0.0" tlng="0"/><send-out mwh="137953.318415392" mcm="12.4607081014231" cmlng="19937.979250621302" tlng="8972.09066277959"/></lng>