<?xml version="1.0" encoding="utf-8"?>
<lng xmlns="http://energy.icis.com/ns/eu-gas-fundamentals" created-on="2017-07-28T07:10:10Z+1"><country>Spain</country><point>Barcelona</point><lso>Enagas</lso><gas-quality>H</gas-quality><plant-type>LNG Peak Shaving/LNG Terminal</plant-type><period type="gas-day" from="2017-07-26T23:00:00Z+1" to="2017-07-27T23:00:00Z+1"/><acquired>2017-07-28T07:10:10Z+1</acquired><state version="8">Provisional</state><capacity mwh="5192498.20653845" mcm="469.015209" cmlng="760000.0" tlng="342000.0" country-percentage="22.9157244082617%"/><stock-level mwh="2617494.51426292" mcm="237.041316919247" cmlng="383107.0" tlng="172398.15" full="50.5402196710528%"/><unloaded-inflow mwh="0" mcm="0" cmlng="0.0" tlng="0"/><send-out mwh="234290.843806104" mcm="21.2174695516257" cmlng="34595.0" tlng="15567.75"/><reloaded mwh="0" mcm="0" cmlng="0.0" tlng="0"/><truck-load mwh="9774.58607620188" mcm="0.885190300578678" cmlng="1430.653" tlng="643.79385"/></lng>