<?xml version="1.0" encoding="utf-8"?>
<demand xmlns="http://energy.icis.com/ns/eu-gas-fundamentals" created-on="2015-12-03T06:06:48Z"><country>Belgium</country><tso>Fluxys</tso><gas-quality>H</gas-quality><period type="intra-day" from="2015-11-30T18:00:00Z" to="2015-11-30T19:00:00Z"/><acquired>2015-12-03T06:06:48Z</acquired><state version="45">Provisional</state><data-type>Actual Flow</data-type><total mwh="21189.1009362612" mcm="1.94307771293219"><industrial mwh="5172.30591227266" mcm="0.474577808474652"/><power mwh="7121.3157471696" mcm="0.653157625319731"/><public-distribution-companies mwh="8895.47927681899" mcm="0.815342279137811"/></total></demand>