<?xml version="1.0" encoding="utf-8"?>
<demand xmlns="http://energy.icis.com/ns/eu-gas-fundamentals" created-on="2015-11-17T05:06:55Z"><country>Belgium</country><tso>Fluxys</tso><gas-quality>H</gas-quality><period type="gas-day" from="2015-11-16T05:00:00Z" to="2015-11-17T05:00:00Z"/><acquired>2015-11-17T05:06:55Z</acquired><state version="1">Provisional</state><data-type>Actual Flow</data-type><total mwh="412032.69661371" mcm="38.1564571699256"><industrial mwh="112795.781660181" mcm="10.4663748956498"/><power mwh="158042.167273" mcm="14.656879157276"/><public-distribution-companies mwh="141194.747680529" mcm="13.0332031169998"/></total></demand>