<?xml version="1.0" encoding="utf-8"?>
<demand xmlns="http://energy.icis.com/ns/eu-gas-fundamentals" created-on="2015-11-17T05:06:55Z"><country>Belgium</country><tso>Fluxys</tso><gas-quality>H</gas-quality><period type="intra-day" from="2015-11-16T18:00:00Z" to="2015-11-16T19:00:00Z"/><acquired>2015-11-17T05:06:55Z</acquired><state version="4">Provisional</state><data-type>Actual Flow</data-type><total mwh="19536.1491519282" mcm="1.80846138675322"><industrial mwh="4650.93498910705" mcm="0.432226356768117"/><power mwh="8129.20777183245" mcm="0.751978578869254"/><public-distribution-companies mwh="6756.0063909887" mcm="0.624256451115848"/></total></demand>