<?xml version="1.0" encoding="utf-8"?>
<demand xmlns="http://energy.icis.com/ns/eu-gas-fundamentals" created-on="2015-11-17T00:06:53Z"><country>Belgium</country><tso>Fluxys</tso><gas-quality>H</gas-quality><period type="intra-day" from="2015-11-14T03:00:00Z" to="2015-11-14T04:00:00Z"/><acquired>2015-11-17T00:06:53Z</acquired><state version="12">Provisional</state><data-type>Actual Flow</data-type><total mwh="14246.2947455843" mcm="1.3206901542777"><industrial mwh="4552.70130996128" mcm="0.420843215850116"/><power mwh="5769.76280277203" mcm="0.538089019036542"/><public-distribution-companies mwh="3923.83063285099" mcm="0.361757919391044"/></total></demand>