<?xml version="1.0" encoding="utf-8"?>
<demand xmlns="http://energy.icis.com/ns/eu-gas-fundamentals" created-on="2015-11-17T09:06:56Z"><country>Belgium</country><tso>Fluxys</tso><gas-quality>H</gas-quality><period type="gas-day" from="2015-11-16T05:00:00Z" to="2015-11-17T05:00:00Z"/><acquired>2015-11-17T09:06:56Z</acquired><state version="3">Provisional</state><data-type>Actual Flow</data-type><total mwh="411695.044588932" mcm="38.1221659543609"><industrial mwh="112879.390156468" mcm="10.4737755822823"/><power mwh="157205.352236363" mcm="14.5778535207195"/><public-distribution-companies mwh="141610.302196101" mcm="13.0705368513591"/></total></demand>