<?xml version="1.0" encoding="utf-8"?>
<lng xmlns="http://energy.icis.com/ns/eu-gas-fundamentals" created-on="2018-03-10T08:05:01Z"><country>Netherlands</country><point>Gate</point><lso>Gate terminal</lso><gas-quality>H</gas-quality><plant-type>LNG Terminal</plant-type><period type="gas-day" from="2018-03-08T05:00:00Z" to="2018-03-09T05:00:00Z"/><acquired>2018-03-10T08:05:01Z</acquired><state version="3">Provisional</state><capacity mwh="3817117.65204852" mcm="333.2476485" cmlng="540000.0" tlng="243000.0" country-percentage="100%"/><stock-level mwh="418506.692773264" mcm="36.5370900143347" cmlng="59205.3048132481" tlng="26642.3871659616" full="10.9639453357867%"/><unloaded-inflow mwh="0" mcm="0" cmlng="0" tlng="0"/><send-out mwh="30577.308" mcm="2.66950534862129" cmlng="4325.710608144" tlng="1946.5697736648"/><reloaded mwh="1320.80579536608" mcm="0.115310940231218" cmlng="186.851754258845" tlng="84.0832894164778"/></lng>