<?xml version="1.0" encoding="utf-8"?>
<lng xmlns="http://energy.icis.com/ns/eu-gas-fundamentals" created-on="2016-11-22T07:20:24Z"><country>Portugal</country><point>Sines</point><lso>REN Atlantico</lso><gas-quality>H</gas-quality><plant-type>LNG Terminal</plant-type><period type="gas-day" from="2016-11-20T05:00:00Z" to="2016-11-21T05:00:00Z"/><acquired>2016-11-22T07:20:24Z</acquired><state version="3">Provisional</state><capacity mwh="2714403.0401314" mcm="240.67885725" cmlng="390000.0" tlng="175500.0" country-percentage="100%"/><stock-level mwh="734864.291" mcm="65.158451113122" cmlng="105583.831602298" tlng="47512.7242210341" full="27.0727773339226%"/><unloaded-inflow mwh="0" mcm="0" cmlng="0" tlng="0"/><send-out mwh="33108.47294" mcm="2.9356397390809" cmlng="4756.95917507332" tlng="2140.63162878299"/><reloaded mwh="0" mcm="0" cmlng="0" tlng="0"/></lng>