<?xml version="1.0" encoding="utf-8"?>
<lng xmlns="http://energy.icis.com/ns/eu-gas-fundamentals" created-on="2016-04-04T10:27:42Z+1"><country>Great Britain</country><point>Milford Haven - Dragon</point><lso>Dragon LNG Ltd</lso><gas-quality>H</gas-quality><plant-type>LNG Terminal</plant-type><period type="gas-day" from="2016-04-01T05:00:00Z+1" to="2016-04-02T05:00:00Z+1"/><acquired>2016-04-04T10:27:42Z+1</acquired><state version="2">Provisional</state><capacity mwh="2261995.64565839" mcm="197.480088" cmlng="320000.0" tlng="144000.0" country-percentage="15.2744630071599%"/><stock-level mwh="1179501.279" mcm="102.974564438313" cmlng="166861.686937572" tlng="75087.7591219074" full="52.144277167991%"/><unloaded-inflow mwh="0" mcm="0" cmlng="0" tlng="0"/><send-out mwh="2553.777" mcm="0.222953615167365" cmlng="361.277724636" tlng="162.5749760862"/><reloaded mwh="0" mcm="0" cmlng="0" tlng="0"/></lng>