<?xml version="1.0" encoding="utf-8"?>
<lng xmlns="http://energy.icis.com/ns/eu-gas-fundamentals" created-on="2016-03-28T10:30:39Z+1"><country>Spain</country><point>Huelva</point><lso>Enagas</lso><gas-quality>H</gas-quality><plant-type>LNG Peak Shaving/LNG Terminal</plant-type><period type="gas-day" from="2013-01-05T23:00:00Z" to="2013-01-06T23:00:00Z"/><acquired>2016-03-28T10:30:39Z+1</acquired><state version="1">Provisional</state><capacity mwh="4167663.03419533" mcm="376.44641775" cmlng="610000.0" tlng="274500.0" country-percentage="18.844609206055%"/><stock-level mwh="1652977.55834829" mcm="149.30605478295" cmlng="241938.0" tlng="108872.10000000001" full="39.6619672131148%"/><unloaded-inflow mwh="155507.275457181" mcm="13.869890555625" cmlng="22475.0" tlng="10113.75"/><send-out mwh="101107.121484141" mcm="9.23959817043406" cmlng="14971.997655474501" tlng="6737.3989449635301"/></lng>