<?xml version="1.0" encoding="utf-8"?>
<lng xmlns="http://energy.icis.com/ns/eu-gas-fundamentals" created-on="2016-03-28T10:30:39Z+1"><country>Spain</country><point>Sagunto</point><lso>Saggas</lso><gas-quality>H</gas-quality><plant-type>LNG Peak Shaving/LNG Terminal</plant-type><period type="gas-day" from="2012-10-15T23:00:00Z+1" to="2012-10-16T23:00:00Z+1"/><acquired>2016-03-28T10:30:39Z+1</acquired><state version="1">Provisional</state><capacity mwh="4099340.68937246" mcm="370.275165" cmlng="600000.0" tlng="270000.0" country-percentage="18.5356811862836%"/><stock-level mwh="1519625.97247157" mcm="137.2610036655" cmlng="222420.0" tlng="100089.0" full="37.07%"/><unloaded-inflow mwh="105938.682737482" mcm="9.448805085525" cmlng="15311.0" tlng="6889.9499999999998"/><send-out mwh="117235.188509874" mcm="23.6871178149884" cmlng="38382.997382481801" tlng="17272.348822116801"/></lng>