<?xml version="1.0" encoding="utf-8"?>
<lng xmlns="http://energy.icis.com/ns/eu-gas-fundamentals" created-on="2017-07-07T07:18:01Z+1"><country>Spain</country><point>Bilbao</point><lso>BBG</lso><gas-quality>H</gas-quality><plant-type>LNG Peak Shaving/LNG Terminal</plant-type><period type="gas-day" from="2015-12-16T23:00:00Z" to="2015-12-17T23:00:00Z"/><acquired>2017-07-07T07:18:01Z+1</acquired><state version="2">Provisional</state><capacity mwh="3074505.51702934" mcm="277.70637375" cmlng="450000.0" tlng="202500.0" country-percentage="13.5685210312076%"/><stock-level mwh="1665469.7785757" mcm="150.825588153702" cmlng="243760.0" tlng="109692" full="54.3111726666668%"/><unloaded-inflow mwh="0" mcm="0" cmlng="0.0" tlng="0"/><send-out mwh="67324.9551166966" mcm="6.09697400908783" cmlng="10045.0" tlng="4520.25"/><reloaded mwh="0" mcm="0" cmlng="0.0" tlng="0"/><truck-load mwh="1795.33213644524" mcm="0.162585973575676" cmlng="262.77300000000002" tlng="118.24785"/></lng>