<?xml version="1.0" encoding="utf-8"?>
<lng xmlns="http://energy.icis.com/ns/eu-gas-fundamentals" created-on="2016-03-28T10:30:39Z+1"><country>Belgium</country><point>Zeebrugge</point><lso>Fluxys</lso><gas-quality>H</gas-quality><plant-type>LNG Terminal</plant-type><period type="gas-day" from="2012-09-05T05:00:00Z+1" to="2012-09-06T05:00:00Z+1"/><acquired>2016-03-28T10:30:39Z+1</acquired><state version="1">Provisional</state><capacity mwh="2536783.35870117" mcm="234.5076045" cmlng="380000.0" tlng="171000.0" country-percentage="100%"/><stock-level mwh="1689429.25570298" mcm="146.96351409" cmlng="270600.389500155" tlng="121770.17527507" full="62.6689758753644%"/><unloaded-inflow mwh="0" mcm="0" cmlng="0.0" tlng="0.0"/><send-out mwh="67122.0702494355" mcm="6.12222081841812" cmlng="10063.539745702101" tlng="4528.5928855659604"/><reloaded mwh="271405.202886624" mcm="25.1704978573574" cmlng="40643.699032964898" tlng="18289.664564834198"/></lng>