<?xml version="1.0" encoding="utf-8"?>
<demand xmlns="http://energy.icis.com/ns/eu-gas-fundamentals" created-on="2015-12-27T00:06:45Z"><country>Belgium</country><tso>Fluxys</tso><gas-quality>L</gas-quality><period type="intra-day" from="2015-12-26T22:00:00Z" to="2015-12-26T23:00:00Z"/><acquired>2015-12-27T00:06:45Z</acquired><state version="2">Provisional</state><data-type>Actual Flow</data-type><total mwh="3790.29392798197" mcm="0.404003687945121"><industrial mwh="438.25210326097" mcm="0.046716388744481"/><public-distribution-companies mwh="3352.041824721" mcm="0.35728729920064"/></total></demand>