<?xml version="1.0" encoding="utf-8"?>
<demand xmlns="http://energy.icis.com/ns/eu-gas-fundamentals" created-on="2016-01-01T01:06:45Z"><country>Belgium</country><tso>Fluxys</tso><gas-quality>L</gas-quality><period type="intra-day" from="2015-12-31T23:00:00Z" to="2016-01-01T00:00:00Z"/><acquired>2016-01-01T01:06:45Z</acquired><state version="2">Provisional</state><data-type>Actual Flow</data-type><total mwh="4603.4048215425" mcm="0.490144397340078"><industrial mwh="428.388919077539" mcm="0.0456006963015766"/><public-distribution-companies mwh="4175.01590246496" mcm="0.444543701038502"/></total></demand>