<?xml version="1.0" encoding="utf-8"?>
<lng xmlns="http://energy.icis.com/ns/eu-gas-fundamentals" created-on="2016-03-28T10:30:39Z+1"><country>Spain</country><point>Huelva</point><lso>Enagas</lso><gas-quality>H</gas-quality><plant-type>LNG Peak Shaving/LNG Terminal</plant-type><period type="gas-day" from="2012-01-29T23:00:00Z" to="2012-01-30T23:00:00Z"/><acquired>2016-03-28T10:30:39Z+1</acquired><state version="1">Provisional</state><capacity mwh="4167663.03419533" mcm="376.44641775" cmlng="610000.0" tlng="274500.0" country-percentage="19.7602850664075%"/><stock-level mwh="2475505.85078795" mcm="221.37147589635" cmlng="358714.0" tlng="161421.29999999999" full="58.8055737704918%"/><unloaded-inflow mwh="817127.595535782" mcm="72.880643601675" cmlng="118097.0" tlng="53143.650000000001"/><send-out mwh="177079.593058049" mcm="15.6404186934173" cmlng="25343.993070802899" tlng="11404.796881861301"/></lng>