<?xml version="1.0" encoding="utf-8"?>
<lng xmlns="http://energy.icis.com/ns/eu-gas-fundamentals" created-on="2016-03-28T10:30:39Z+1"><country>France</country><point>Fos Tonkin</point><lso>Elengy</lso><market-area>PEG SUD</market-area><gas-quality>H</gas-quality><plant-type>LNG Terminal</plant-type><period type="gas-day" from="2012-02-17T05:00:00Z" to="2012-02-18T05:00:00Z"/><acquired>2016-03-28T10:30:39Z+1</acquired><state version="1">Provisional</state><capacity mwh="1031062.47551227" mcm="92.56879125" cmlng="150000.0" tlng="67500.0" country-percentage="17.8571428571429%"/><stock-level mwh="590859.966" mcm="53.04740774748" cmlng="83587.777670088006" tlng="37614.499951539598" full="57.3059311147481%"/><unloaded-inflow mwh="438579.236" mcm="39.37564380808" cmlng="62044.927358448003" tlng="27920.2173113016"/><send-out mwh="69007.181" mcm="6.19546471018" cmlng="9762.3078817080004" tlng="4393.0385467686001"/><reloaded mwh="0" mcm="0" cmlng="0.0" tlng="0.0"/></lng>