<?xml version="1.0" encoding="utf-8"?>
<lng xmlns="http://energy.icis.com/ns/eu-gas-fundamentals" created-on="2016-03-28T10:30:39Z+1"><country>Spain</country><point>Barcelona</point><lso>Enagas</lso><gas-quality>H</gas-quality><plant-type>LNG Peak Shaving/LNG Terminal</plant-type><period type="gas-day" from="2009-12-05T23:00:00Z" to="2009-12-06T23:00:00Z"/><acquired>2016-03-28T10:30:39Z+1</acquired><state version="1">Provisional</state><capacity mwh="5739076.96512144" mcm="518.385231" cmlng="840000.0" tlng="378000.0" country-percentage="28.6006128702758%"/><stock-level mwh="1605537.87053661" mcm="143.574812354025" cmlng="232651.0" tlng="104692.95" full="27.6965476190476%"/><unloaded-inflow mwh="138590.021241706" mcm="12.36101925825" cmlng="20030.0" tlng="9013.5"/><send-out mwh="192080.590464792" mcm="17.3497832253937" cmlng="28113.875623379201" tlng="12651.2440305206"/></lng>