<?xml version="1.0" encoding="utf-8"?>
<lng xmlns="http://energy.icis.com/ns/eu-gas-fundamentals" created-on="2016-03-28T10:30:39Z+1"><country>Great Britain</country><point>Milford Haven - Dragon</point><lso>Dragon LNG Ltd</lso><gas-quality>H</gas-quality><plant-type>LNG Terminal</plant-type><period type="gas-day" from="2010-10-08T06:00:00Z+1" to="2010-10-09T06:00:00Z+1"/><acquired>2016-03-28T10:30:39Z+1</acquired><state version="1">Provisional</state><capacity mwh="2261995.64565839" mcm="197.480088" cmlng="320000.0" tlng="144000.0" country-percentage="15.2744630071599%"/><stock-level mwh="1945643.69" mcm="169.86146187121" cmlng="275246.32153691998" tlng="123860.84469161399" full="86.0144754802874%"/><unloaded-inflow mwh="0" mcm="0" cmlng="0.0" tlng="0.0"/><send-out mwh="2255.662" mcm="0.196927138703047" cmlng="319.10399181600002" tlng="143.59679631719999"/><reloaded mwh="0" mcm="0" cmlng="0.0" tlng="0.0"/></lng>