<?xml version="1.0" encoding="utf-8"?>
<lng xmlns="http://energy.icis.com/ns/eu-gas-fundamentals" created-on="2017-07-07T07:43:32Z+1"><country>Spain</country><point>Bilbao</point><lso>BBG</lso><gas-quality>H</gas-quality><plant-type>LNG Peak Shaving/LNG Terminal</plant-type><period type="gas-day" from="2015-05-03T23:00:00Z+1" to="2015-05-04T23:00:00Z+1"/><acquired>2017-07-07T07:43:32Z+1</acquired><state version="2">Provisional</state><capacity mwh="3074505.51702934" mcm="277.70637375" cmlng="450000.0" tlng="202500.0" country-percentage="13.5685210312076%"/><stock-level mwh="1288948.73329344" mcm="116.727696473248" cmlng="188655.0" tlng="84894.75" full="42.0327754444446%"/><unloaded-inflow mwh="878659.350847939" mcm="79.3653811105462" cmlng="126990.0" tlng="57145.5"/><send-out mwh="80690.205465789" mcm="7.30733625681786" cmlng="11558.0" tlng="5201.1"/><reloaded mwh="0" mcm="0" cmlng="0.0" tlng="0"/><truck-load mwh="897.666068222621" mcm="0.0812929867878378" cmlng="131.38650000000001" tlng="59.123925"/></lng>