<?xml version="1.0" encoding="utf-8"?>
<lng xmlns="http://energy.icis.com/ns/eu-gas-fundamentals" created-on="2016-05-31T07:20:42Z+1"><country>Portugal</country><point>Sines</point><lso>REN Atlantico</lso><gas-quality>H</gas-quality><plant-type>LNG Terminal</plant-type><period type="gas-day" from="2016-05-28T05:00:00Z+1" to="2016-05-29T05:00:00Z+1"/><acquired>2016-05-31T07:20:42Z+1</acquired><state version="3">Provisional</state><capacity mwh="2714403.0401314" mcm="240.67885725" cmlng="390000.0" tlng="175500.0" country-percentage="100%"/><stock-level mwh="1077344.523" mcm="95.5252572394829" cmlng="154790.706375594" tlng="69655.8178690173" full="39.6899247116909%"/><unloaded-inflow mwh="0" mcm="0" cmlng="0" tlng="0"/><send-out mwh="32593.91372" mcm="2.89001514935488" cmlng="4683.02833546216" tlng="2107.36275095797"/><reloaded mwh="0" mcm="0" cmlng="0" tlng="0"/></lng>