<?xml version="1.0" encoding="utf-8"?>
<lng xmlns="http://energy.icis.com/ns/eu-gas-fundamentals" created-on="2017-12-22T11:10:49Z"><country>Spain</country><point>Cartagena</point><lso>Enagas</lso><gas-quality>H</gas-quality><plant-type>LNG Peak Shaving/LNG Terminal</plant-type><period type="gas-day" from="2017-12-23T23:00:00Z" to="2017-12-24T23:00:00Z"/><acquired>2017-12-22T11:10:49Z</acquired><state version="49">Forecast</state><capacity mwh="4010521.64110272" mcm="362.252536425" cmlng="587000.0" tlng="264150.0" country-percentage="17.6993818784864%"/><stock-level mwh="829232.755766535" mcm="74.9008971761903" cmlng="119846.52249267" tlng="53930.9351217015" full="20.6764313965536%"/><unloaded-inflow mwh="0" mcm="0" cmlng="0.0" tlng="0"/><send-out mwh="8002.69565005107" mcm="0.722847813051876" cmlng="1156.6055942149301" tlng="520.472517396719"/></lng>