<?xml version="1.0" encoding="utf-8"?>
<lng xmlns="http://energy.icis.com/ns/eu-gas-fundamentals" created-on="2015-02-03T13:25:07Z"><country>Italy</country><point>Porto Levante</point><lso>Adriatic LNG</lso><gas-quality>H</gas-quality><plant-type>LNG Terminal</plant-type><period type="gas-day" from="2015-02-01T05:00:00Z" to="2015-02-02T05:00:00Z"/><acquired>2015-02-03T13:25:07Z</acquired><state version="1">Provisional</state><capacity mwh="1673624.5" mcm="154.28131875" cmlng="250000.0" tlng="112500.0" country-percentage="71.4285714285714%"/><stock-level mwh="365703.296735867" mcm="33.7119747539739" cmlng="54627.4413310553" tlng="24582.3485989749" full="21.8509765324222%"/><unloaded-inflow mwh="927551.804722222" mcm="85.5053900331211" cmlng="138554.347872271" tlng="62349.4565425219"/><send-out mwh="187048.811388889" mcm="17.2428984468726" cmlng="27940.677760885" tlng="12573.3049923982"/></lng>