<?xml version="1.0" encoding="utf-8"?>
<lng xmlns="http://energy.icis.com/ns/eu-gas-fundamentals" created-on="2016-05-14T08:10:02Z+1"><country>Spain</country><point>Huelva</point><lso>Enagas</lso><gas-quality>H</gas-quality><plant-type>LNG Peak Shaving/LNG Terminal</plant-type><period type="gas-day" from="2016-05-12T23:00:00Z+1" to="2016-05-13T23:00:00Z+1"/><acquired>2016-05-14T08:10:02Z+1</acquired><state version="3">Provisional</state><capacity mwh="4232569.26177706" mcm="382.3091078625" cmlng="619500.0" tlng="278775.0" country-percentage="18.6793306196291%"/><stock-level mwh="1419908.23857969" mcm="128.587439990184" cmlng="207825.0" tlng="93521.25" full="33.6344171105732%"/><unloaded-inflow mwh="0" mcm="0" cmlng="0.0" tlng="0"/><send-out mwh="98045.0827847596" mcm="8.87900066804939" cmlng="15786.304" tlng="7103.8368"/><reloaded mwh="0" mcm="0" cmlng="0.0" tlng="0"/></lng>