<?xml version="1.0" encoding="utf-8"?>
<lng xmlns="http://energy.icis.com/ns/eu-gas-fundamentals" created-on="2017-12-23T08:05:24Z"><country>Netherlands</country><point>Gate</point><lso>Gate terminal</lso><gas-quality>H</gas-quality><plant-type>LNG Terminal</plant-type><period type="gas-day" from="2017-12-21T05:00:00Z" to="2017-12-22T05:00:00Z"/><acquired>2017-12-23T08:05:24Z</acquired><state version="3">Provisional</state><capacity mwh="3817117.65204852" mcm="333.2476485" cmlng="540000.0" tlng="243000.0" country-percentage="100%"/><stock-level mwh="2017810.15666641" mcm="176.161845435293" cmlng="285455.567243284" tlng="128455.005259478" full="52.8621420820898%"/><unloaded-inflow mwh="0" mcm="0" cmlng="0" tlng="0"/><send-out mwh="4515.069" mcm="0.394181228932717" cmlng="638.737781292" tlng="287.4320015814"/><reloaded mwh="2030.26192827001" mcm="0.17724892840858" cmlng="287.217094468479" tlng="129.247692510821"/></lng>