<?xml version="1.0" encoding="utf-8"?>
<lng xmlns="http://energy.icis.com/ns/eu-gas-fundamentals" created-on="2017-10-28T14:10:44Z+1"><country>Spain</country><point>Bilbao</point><lso>BBG</lso><gas-quality>H</gas-quality><plant-type>LNG Peak Shaving/LNG Terminal</plant-type><period type="gas-day" from="2017-11-20T23:00:00Z" to="2017-11-21T23:00:00Z"/><acquired>2017-10-28T14:10:44Z+1</acquired><state version="28">Forecast</state><capacity mwh="3074505.51702934" mcm="277.70637375" cmlng="450000.0" tlng="202500.0" country-percentage="13.5685210312076%"/><stock-level mwh="1991364.42728376" mcm="179.871068974388" cmlng="287805.92658203997" tlng="129512.666961918" full="64.7702343109752%"/><unloaded-inflow mwh="0" mcm="0" cmlng="0.0" tlng="0"/><send-out mwh="99983.8601338311" mcm="9.03109624539616" cmlng="14450.3673535622" tlng="6502.66530910299"/></lng>