<?xml version="1.0" encoding="utf-8"?>
<lng xmlns="http://energy.icis.com/ns/eu-gas-fundamentals" created-on="2017-09-19T11:10:22Z+1"><country>Spain</country><point>Cartagena</point><lso>Enagas</lso><gas-quality>H</gas-quality><plant-type>LNG Peak Shaving/LNG Terminal</plant-type><period type="gas-day" from="2017-09-28T23:00:00Z+1" to="2017-09-29T23:00:00Z+1"/><acquired>2017-09-19T11:10:22Z+1</acquired><state version="47">Forecast</state><capacity mwh="4010521.64110272" mcm="362.252536425" cmlng="587000.0" tlng="264150.0" country-percentage="17.6993818784864%"/><stock-level mwh="1351567.46916243" mcm="122.081062681659" cmlng="195337.99161563901" tlng="87902.0962270376" full="33.7005404810835%"/><unloaded-inflow mwh="0" mcm="0" cmlng="0.0" tlng="0"/><send-out mwh="10162.5509218682" mcm="0.917937908691286" cmlng="1468.76299708484" tlng="660.943348688178"/></lng>