<?xml version="1.0" encoding="utf-8"?>
<lng xmlns="http://energy.icis.com/ns/eu-gas-fundamentals" created-on="2018-02-01T23:11:07Z"><country>Spain</country><point>Barcelona</point><lso>Enagas</lso><gas-quality>H</gas-quality><plant-type>LNG Peak Shaving/LNG Terminal</plant-type><period type="gas-day" from="2018-02-10T23:00:00Z" to="2018-02-11T23:00:00Z"/><acquired>2018-02-01T23:11:07Z</acquired><state version="30">Forecast</state><capacity mwh="5192498.20653845" mcm="469.015209" cmlng="760000.0" tlng="342000.0" country-percentage="22.9157244082617%"/><stock-level mwh="1824248.16606282" mcm="164.776202290536" cmlng="263653.11469656101" tlng="118643.901613452" full="35.1323793191823%"/><unloaded-inflow mwh="0" mcm="0" cmlng="0.0" tlng="0"/><send-out mwh="184750.39354833" mcm="16.6876792241914" cmlng="26701.420128359499" tlng="12015.6390577618"/></lng>