<?xml version="1.0" encoding="utf-8"?>
<lng xmlns="http://energy.icis.com/ns/eu-gas-fundamentals" created-on="2018-06-27T07:10:16Z+1"><country>Spain</country><point>Cartagena</point><lso>Enagas</lso><gas-quality>H</gas-quality><plant-type>LNG Peak Shaving/LNG Terminal</plant-type><period type="gas-day" from="2018-06-25T23:00:00Z+1" to="2018-06-26T23:00:00Z+1"/><acquired>2018-06-27T07:10:16Z+1</acquired><state version="62">Provisional</state><capacity mwh="4010521.64110272" mcm="362.252536425" cmlng="587000.0" tlng="264150.0" country-percentage="17.6993818784864%"/><stock-level mwh="1130560.54258927" mcm="102.384000582238" cmlng="165470.0" tlng="74461.5" full="28.2631563032369%"/><unloaded-inflow mwh="0" mcm="0" cmlng="0.0" tlng="0"/><send-out mwh="4089.36764412527" mcm="0.370334717589039" cmlng="598.540295232396" tlng="269.343132854578"/><reloaded mwh="0" mcm="0" cmlng="0.0" tlng="0"/><truck-load mwh="6782.36584879314" mcm="0.614213677952552" cmlng="992.69799999999998" tlng="446.7141"/></lng>