<?xml version="1.0" encoding="utf-8"?>
<lng xmlns="http://energy.icis.com/ns/eu-gas-fundamentals" created-on="2016-06-09T08:10:04Z+1"><country>Spain</country><point>Mugardos</point><lso>Reganosa</lso><gas-quality>H</gas-quality><plant-type>LNG Peak Shaving/LNG Terminal</plant-type><period type="gas-day" from="2016-06-07T23:00:00Z+1" to="2016-06-08T23:00:00Z+1"/><acquired>2016-06-09T08:10:04Z+1</acquired><state version="3">Provisional</state><capacity mwh="2049670.34468623" mcm="185.1375825" cmlng="300000.0" tlng="135000.0" country-percentage="9.04568068747173%"/><stock-level mwh="561340.514661879" mcm="50.8352144046612" cmlng="82161.0" tlng="36972.45" full="27.4580740000001%"/><unloaded-inflow mwh="0" mcm="0" cmlng="0.0" tlng="0"/><send-out mwh="36405.3461001396" mcm="3.2968822419512" cmlng="5495.2965000000004" tlng="2472.883425"/><reloaded mwh="0" mcm="0" cmlng="0.0" tlng="0"/></lng>