<?xml version="1.0" encoding="utf-8"?>
<lng xmlns="http://energy.icis.com/ns/eu-gas-fundamentals" created-on="2017-10-02T11:10:22Z+1"><country>Spain</country><point>Bilbao</point><lso>BBG</lso><gas-quality>H</gas-quality><plant-type>LNG Peak Shaving/LNG Terminal</plant-type><period type="gas-day" from="2017-10-22T23:00:00Z+1" to="2017-10-23T23:00:00Z+1"/><acquired>2017-10-02T11:10:22Z+1</acquired><state version="32">Forecast</state><capacity mwh="3074505.51702934" mcm="277.70637375" cmlng="450000.0" tlng="202500.0" country-percentage="13.5685210312076%"/><stock-level mwh="1574983.80169742" mcm="142.261263758274" cmlng="227627.683907923" tlng="102432.457758565" full="51.2272231412097%"/><unloaded-inflow mwh="0" mcm="0" cmlng="0.0" tlng="0"/><send-out mwh="98610.3274080103" mcm="8.90703115902637" cmlng="14251.8547892975" tlng="6413.33465518387"/></lng>