<?xml version="1.0" encoding="utf-8"?>
<lng xmlns="http://energy.icis.com/ns/eu-gas-fundamentals" created-on="2017-08-25T11:10:29Z+1"><country>Spain</country><point>Bilbao</point><lso>BBG</lso><gas-quality>H</gas-quality><plant-type>LNG Peak Shaving/LNG Terminal</plant-type><period type="gas-day" from="2017-09-24T23:00:00Z+1" to="2017-09-25T23:00:00Z+1"/><acquired>2017-08-25T11:10:29Z+1</acquired><state version="23">Forecast</state><capacity mwh="3074505.51702934" mcm="277.70637375" cmlng="450000.0" tlng="202500.0" country-percentage="13.5685210312076%"/><stock-level mwh="1579026.77517484" mcm="142.626447524367" cmlng="228212.002735694" tlng="102695.401231062" full="51.3587230996591%"/><unloaded-inflow mwh="0" mcm="0" cmlng="0.0" tlng="0"/><send-out mwh="89453.2618651678" mcm="8.07991426103786" cmlng="12928.4115775871" tlng="5817.78520991419"/></lng>