<?xml version="1.0" encoding="utf-8"?>
<lng xmlns="http://energy.icis.com/ns/eu-gas-fundamentals" created-on="2017-07-07T07:14:09Z+1"><country>Spain</country><point>Huelva</point><lso>Enagas</lso><gas-quality>H</gas-quality><plant-type>LNG Peak Shaving/LNG Terminal</plant-type><period type="gas-day" from="2016-01-21T23:00:00Z" to="2016-01-22T23:00:00Z"/><acquired>2017-07-07T07:14:09Z+1</acquired><state version="2">Provisional</state><capacity mwh="4232569.26177706" mcm="382.3091078625" cmlng="619500.0" tlng="278775.0" country-percentage="18.6793306196291%"/><stock-level mwh="3434570.117694" mcm="311.036000004355" cmlng="502704.0" tlng="226216.8" full="81.357203793382%"/><unloaded-inflow mwh="937520.324921987" mcm="84.6820304302361" cmlng="135497.0" tlng="60973.65"/><send-out mwh="92359.864352683" mcm="8.36414508505975" cmlng="18455.0" tlng="8304.75"/><reloaded mwh="0" mcm="0" cmlng="0.0" tlng="0"/><truck-load mwh="7680.03191701576" mcm="0.69550666474039" cmlng="1124.0844999999999" tlng="505.838025"/></lng>