<?xml version="1.0" encoding="utf-8"?>
<lng xmlns="http://energy.icis.com/ns/eu-gas-fundamentals" created-on="2016-03-28T10:30:39Z+1"><country>Spain</country><point>Cartagena</point><lso>Enagas</lso><gas-quality>H</gas-quality><plant-type>LNG Peak Shaving/LNG Terminal</plant-type><period type="gas-day" from="2011-12-29T23:00:00Z" to="2011-12-30T23:00:00Z"/><acquired>2016-03-28T10:30:39Z+1</acquired><state version="1">Provisional</state><capacity mwh="2985686.46875961" mcm="269.683745175" cmlng="437000.0" tlng="196650.0" country-percentage="14.8791283622744%"/><stock-level mwh="1353373.23857969" mcm="121.025054805525" cmlng="196111.0" tlng="88249.949999999997" full="44.8766590389016%"/><unloaded-inflow mwh="181080.351768182" mcm="16.150785572025" cmlng="26171.0" tlng="11776.950000000001"/><send-out mwh="86973.8679433473" mcm="7.70172120719581" cmlng="12479.996394890501" tlng="5615.9983777007301"/></lng>