<?xml version="1.0" encoding="utf-8"?>
<lng xmlns="http://energy.icis.com/ns/eu-gas-fundamentals" created-on="2018-01-18T10:10:54Z"><country>Spain</country><point>Barcelona</point><lso>Enagas</lso><gas-quality>H</gas-quality><plant-type>LNG Peak Shaving/LNG Terminal</plant-type><period type="gas-day" from="2018-01-19T23:00:00Z" to="2018-01-20T23:00:00Z"/><acquired>2018-01-18T10:10:54Z</acquired><state version="48">Forecast</state><capacity mwh="5192498.20653845" mcm="469.015209" cmlng="760000.0" tlng="342000.0" country-percentage="22.9157244082617%"/><stock-level mwh="4540504.38840518" mcm="410.123514729713" cmlng="656225.47774303495" tlng="295301.464984366" full="87.4435427380166%"/><unloaded-inflow mwh="913324.153964311" mcm="82.496498201371" cmlng="132000.0" tlng="59400"/><send-out mwh="89045.2237577622" mcm="8.04305799828869" cmlng="12869.439054038099" tlng="5791.24757431714"/></lng>