<?xml version="1.0" encoding="utf-8"?>
<lng xmlns="http://energy.icis.com/ns/eu-gas-fundamentals" created-on="2016-12-08T08:10:01Z"><country>Spain</country><point>Barcelona</point><lso>Enagas</lso><gas-quality>H</gas-quality><plant-type>LNG Peak Shaving/LNG Terminal</plant-type><period type="gas-day" from="2016-12-06T23:00:00Z" to="2016-12-07T23:00:00Z"/><acquired>2016-12-08T08:10:01Z</acquired><state version="3">Provisional</state><capacity mwh="5192498.20653845" mcm="469.015209" cmlng="760000.0" tlng="342000.0" country-percentage="22.9157244082617%"/><stock-level mwh="2657191.30261321" mcm="240.636273446087" cmlng="388923.0" tlng="175015.35" full="51.3067100657896%"/><unloaded-inflow mwh="934939.4922748" mcm="84.4489153254701" cmlng="135124.0" tlng="60805.8"/><send-out mwh="176441.252742869" mcm="15.9785881808539" cmlng="26095.0" tlng="11742.75"/><reloaded mwh="0" mcm="0" cmlng="0.0" tlng="0"/><truck-load mwh="8078.99461400359" mcm="0.73163688109054" cmlng="1182.4784999999999" tlng="532.115325"/></lng>