<?xml version="1.0" encoding="utf-8"?>
<lng xmlns="http://energy.icis.com/ns/eu-gas-fundamentals" created-on="2018-01-08T19:13:01Z"><country>France</country><point>Montoir de Bretagne</point><lso>Elengy</lso><market-area>PEG NORD</market-area><gas-quality>H</gas-quality><plant-type>LNG Terminal</plant-type><period type="gas-day" from="2018-01-07T05:00:00Z" to="2018-01-08T05:00:00Z"/><acquired>2018-01-08T19:13:01Z</acquired><state version="4">Provisional</state><capacity mwh="2495615.34248854" mcm="222.165099" cmlng="360000.0" tlng="162000.0" country-percentage="25.5319148921499%"/><stock-level mwh="2198377.01812424" mcm="195.70429767589" cmlng="311000.0" tlng="139950" full="88.0895777765212%"/><unloaded-inflow mwh="0" mcm="0" cmlng="0" tlng="0"/><send-out mwh="39132.496" mcm="3.48365980122877" cmlng="5535.995944128" tlng="2491.1981748576"/><reloaded mwh="0" mcm="0" cmlng="0" tlng="0"/></lng>