<?xml version="1.0" encoding="utf-8"?>
<lng xmlns="http://energy.icis.com/ns/eu-gas-fundamentals" created-on="2017-02-13T11:37:45Z"><country>Greece</country><point>Revithoussa</point><lso>DESFA</lso><gas-quality>H</gas-quality><plant-type>LNG Terminal</plant-type><period type="gas-day" from="2017-02-12T06:00:00Z" to="2017-02-13T06:00:00Z"/><acquired>2017-02-13T11:37:45Z</acquired><state version="3">Provisional</state><capacity mwh="882702.427431675" mcm="80.22628575" cmlng="130000.0" tlng="58500.0" country-percentage="100%"/><stock-level mwh="175885.520285181" mcm="15.9857292459735" cmlng="25903.540000000001" tlng="11656.593" full="19.9258%"/><unloaded-inflow mwh="0" mcm="0" cmlng="0" tlng="0"/><send-out mwh="6189.67" mcm="0.56256131022891" cmlng="911.58364925" tlng="410.2126421625"/></lng>