<?xml version="1.0" encoding="utf-8"?>
<lng xmlns="http://energy.icis.com/ns/eu-gas-fundamentals" created-on="2015-07-15T04:10:00Z+1"><country>Spain</country><point>Bilbao</point><lso>BBG</lso><gas-quality>H</gas-quality><plant-type>LNG Peak Shaving/LNG Terminal</plant-type><period type="gas-day" from="2015-07-13T23:00:00Z+1" to="2015-07-14T23:00:00Z+1"/><acquired>2015-07-15T04:10:00Z+1</acquired><state version="1">Provisional</state><capacity mwh="3074505.51702934" mcm="277.70637375" cmlng="450000.0" tlng="202500.0" country-percentage="13.5685210312076%"/><stock-level mwh="856672.651107121" mcm="77.5806070578599" cmlng="125384.0" tlng="56422.8" full="27.9361996666668%"/><unloaded-inflow mwh="0" mcm="0" cmlng="0.0" tlng="0"/><send-out mwh="122880.510672252" mcm="11.1281066358462" cmlng="18032.167000000001" tlng="8114.47515"/><reloaded mwh="0" mcm="0" cmlng="0.0" tlng="0"/></lng>