<?xml version="1.0" encoding="utf-8"?>
<lng xmlns="http://energy.icis.com/ns/eu-gas-fundamentals" created-on="2017-07-26T11:04:57Z+1"><country>Italy</country><point>Panigaglia</point><lso>GNL Italia</lso><gas-quality>H</gas-quality><plant-type>LNG Terminal</plant-type><period type="gas-day" from="2012-11-19T05:00:00Z" to="2012-11-20T05:00:00Z"/><acquired>2017-07-26T11:04:57Z+1</acquired><state version="3">Provisional</state><capacity mwh="683880" mcm="61.7125275" cmlng="100000.0" tlng="45000.0" country-percentage="20.5128205128205%"/><stock-level mwh="480004.3424" mcm="43.3150277541081" cmlng="70188.3872024332" tlng="31584.7742410949" full="70.1883872024332%"/><unloaded-inflow mwh="430924.742" mcm="38.8861422926616" cmlng="63011.7479674797" tlng="28355.2865853659"/><send-out mwh="37674.8519" mcm="3.39973435973735" cmlng="5508.98577235772" tlng="2479.04359756098"/></lng>