<?xml version="1.0" encoding="utf-8"?>
<lng xmlns="http://energy.icis.com/ns/eu-gas-fundamentals" created-on="2018-01-15T11:10:37Z"><country>Spain</country><point>Cartagena</point><lso>Enagas</lso><gas-quality>H</gas-quality><plant-type>LNG Peak Shaving/LNG Terminal</plant-type><period type="gas-day" from="2018-02-22T23:00:00Z" to="2018-02-23T23:00:00Z"/><acquired>2018-01-15T11:10:37Z</acquired><state version="13">Forecast</state><capacity mwh="4010521.64110272" mcm="362.252536425" cmlng="587000.0" tlng="264150.0" country-percentage="17.6993818784864%"/><stock-level mwh="956635.09358605" mcm="86.4085822485252" cmlng="138259.600170711" tlng="62216.82007682" full="23.8531338113667%"/><unloaded-inflow mwh="0" mcm="0" cmlng="0.0" tlng="0"/><send-out mwh="12759.5973684466" mcm="1.15251753365695" cmlng="1844.10632886948" tlng="829.847847991266"/></lng>