<?xml version="1.0" encoding="utf-8"?>
<lng xmlns="http://energy.icis.com/ns/eu-gas-fundamentals" created-on="2015-08-11T11:25:06Z+1"><country>Italy</country><point>Porto Levante</point><lso>Adriatic LNG</lso><gas-quality>H</gas-quality><plant-type>LNG Terminal</plant-type><period type="gas-day" from="2014-06-06T05:00:00Z+1" to="2014-06-07T05:00:00Z+1"/><acquired>2015-08-11T11:25:06Z+1</acquired><state version="1">Provisional</state><capacity mwh="1673624.5" mcm="154.28131875" cmlng="250000.0" tlng="112500.0" country-percentage="71.4285714285714%"/><stock-level mwh="890729.3056" mcm="82.1109465816496" cmlng="133053.935575154" tlng="59874.2710088195" full="53.2215742300619%"/><unloaded-inflow mwh="927807.4594" mcm="85.5289572913873" cmlng="138592.536647259" tlng="62366.6414912664"/><send-out mwh="231111.115" mcm="21.3047356799467" cmlng="34522.5459773085" tlng="15535.1456897888"/></lng>