<?xml version="1.0" encoding="utf-8"?>
<lng xmlns="http://energy.icis.com/ns/eu-gas-fundamentals" created-on="2018-03-07T11:10:42Z"><country>Spain</country><point>Huelva</point><lso>Enagas</lso><gas-quality>H</gas-quality><plant-type>LNG Peak Shaving/LNG Terminal</plant-type><period type="gas-day" from="2018-03-17T23:00:00Z" to="2018-03-18T23:00:00Z"/><acquired>2018-03-07T11:10:42Z</acquired><state version="37">Forecast</state><capacity mwh="4232569.26177706" mcm="382.3091078625" cmlng="619500.0" tlng="278775.0" country-percentage="18.6793306196291%"/><stock-level mwh="736212.376839207" mcm="66.498781137147" cmlng="106402.56618744" tlng="47881.154784348" full="17.3939829759598%"/><unloaded-inflow mwh="0" mcm="0" cmlng="0.0" tlng="0"/><send-out mwh="92927.4885466508" mcm="8.39372566516648" cmlng="13430.531137181801" tlng="6043.73901173181"/></lng>