<?xml version="1.0" encoding="utf-8"?>
<lng xmlns="http://energy.icis.com/ns/eu-gas-fundamentals" created-on="2018-04-20T13:15:03Z+1"><country>Spain</country><point>Barcelona</point><lso>Enagas</lso><gas-quality>H</gas-quality><plant-type>LNG Peak Shaving/LNG Terminal</plant-type><period type="gas-day" from="2018-05-01T23:00:00Z+1" to="2018-05-02T23:00:00Z+1"/><acquired>2018-04-20T13:15:03Z+1</acquired><state version="12">Forecast</state><capacity mwh="5192498.20653845" mcm="469.015209" cmlng="760000.0" tlng="342000.0" country-percentage="22.9157244082617%"/><stock-level mwh="2640089.22708791" mcm="238.467487395967" cmlng="381564.17572333402" tlng="171703.8790755" full="50.8442973319372%"/><unloaded-inflow mwh="0" mcm="0" cmlng="0.0" tlng="0"/><send-out mwh="111456.452006021" mcm="10.0673643114942" cmlng="16108.4666390742" tlng="7248.80998758339"/></lng>