<?xml version="1.0" encoding="utf-8"?>
<lng xmlns="http://energy.icis.com/ns/eu-gas-fundamentals" created-on="2013-07-05T09:56:40Z+1"><country>Italy</country><point>Porto Levante</point><lso>Adriatic LNG</lso><gas-quality>H</gas-quality><plant-type>LNG Terminal</plant-type><period type="gas-day" from="2013-02-07T05:00:00Z" to="2013-02-08T05:00:00Z"/><acquired>2013-07-05T09:56:40Z+1</acquired><state version="1">Provisional</state><capacity mwh="1673624.5" mcm="154.28131875" cmlng="250000.0" tlng="112500.0" country-percentage="71.4285714285714%"/><stock-level mwh="577114.539093045" mcm="53.2006983413" cmlng="86207.291285029103" tlng="38793.281078263099" full="34.4829165140255%"/><unloaded-inflow mwh="0" mcm="0" cmlng="0.0" tlng="0.0"/><send-out mwh="230913.461388889" mcm="21.2865151892" cmlng="34493.021192759901" tlng="15521.859536742"/></lng>