<?xml version="1.0" encoding="utf-8"?>
<lng xmlns="http://energy.icis.com/ns/eu-gas-fundamentals" created-on="2014-07-29T07:30:59Z+1"><country>Spain</country><point>Cartagena</point><lso>Enagas</lso><gas-quality>H</gas-quality><plant-type>LNG Peak Shaving/LNG Terminal</plant-type><period type="gas-day" from="2014-06-30T23:00:00Z+1" to="2014-07-01T23:00:00Z+1"/><acquired>2014-07-29T07:30:59Z+1</acquired><state version="1">Provisional</state><capacity mwh="4010521.64110272" mcm="362.252536425" cmlng="587000.0" tlng="264150.0" country-percentage="18.5378177798832%"/><stock-level mwh="1880101.58587672" mcm="170.262727745843" cmlng="275181.0" tlng="123831.45" full="47.0011140366697%"/><unloaded-inflow mwh="529861.686743654" mcm="47.8600434442592" cmlng="76579.320000000007" tlng="34460.694"/><send-out mwh="46997.8057051666" mcm="4.25613948604768" cmlng="7677.9980529197101" tlng="3455.09912381387"/><reloaded mwh="0" mcm="0" cmlng="0.0" tlng="0"/></lng>