<?xml version="1.0" encoding="utf-8"?>
<lng xmlns="http://energy.icis.com/ns/eu-gas-fundamentals" created-on="2018-04-17T10:25:18Z+1"><country>Italy</country><point>Panigaglia</point><lso>GNL Italia</lso><gas-quality>H</gas-quality><plant-type>LNG Terminal</plant-type><period type="gas-day" from="2018-04-16T05:00:00Z+1" to="2018-04-17T05:00:00Z+1"/><acquired>2018-04-17T10:25:18Z+1</acquired><state version="2">Provisional</state><capacity mwh="683880" mcm="61.7125275" cmlng="100000.0" tlng="45000.0" country-percentage="20.5128205128205%"/><stock-level mwh="58844.43" mcm="5.31005220886242" cmlng="8604.4964028777" tlng="3872.02338129496" full="8.60449640287771%"/><unloaded-inflow mwh="0" mcm="0" cmlng="0" tlng="0"/><send-out mwh="18564.700605" mcm="1.67525676524439" cmlng="2714.61376337954" tlng="1221.57619352079"/></lng>