<?xml version="1.0" encoding="utf-8"?>
<lng xmlns="http://energy.icis.com/ns/eu-gas-fundamentals" created-on="2016-06-05T08:05:25Z+1"><country>Netherlands</country><point>Gate</point><lso>Gate terminal</lso><gas-quality>H</gas-quality><plant-type>LNG Terminal</plant-type><period type="gas-day" from="2016-06-03T05:00:00Z+1" to="2016-06-04T05:00:00Z+1"/><acquired>2016-06-05T08:05:25Z+1</acquired><state version="3">Provisional</state><capacity mwh="3817117.65204852" mcm="333.2476485" cmlng="540000.0" tlng="243000.0" country-percentage="100%"/><stock-level mwh="2051481.47058506" mcm="179.101468262814" cmlng="290218.980680727" tlng="130598.541306327" full="53.7442556816164%"/><unloaded-inflow mwh="800971.9871281" mcm="69.927640580207" cmlng="113311.905075038" tlng="50990.3572837671"/><send-out mwh="55764.722" mcm="4.86845420281535" cmlng="7888.923691896" tlng="3550.0156613532"/><reloaded mwh="0" mcm="0" cmlng="0" tlng="0"/></lng>