<?xml version="1.0" encoding="utf-8"?>
<lng xmlns="http://energy.icis.com/ns/eu-gas-fundamentals" created-on="2017-07-07T07:11:12Z+1"><country>Spain</country><point>Bilbao</point><lso>BBG</lso><gas-quality>H</gas-quality><plant-type>LNG Peak Shaving/LNG Terminal</plant-type><period type="gas-day" from="2016-03-10T23:00:00Z" to="2016-03-11T23:00:00Z"/><acquired>2017-07-07T07:11:12Z+1</acquired><state version="2">Provisional</state><capacity mwh="3074505.51702934" mcm="277.70637375" cmlng="450000.0" tlng="202500.0" country-percentage="13.5685210312076%"/><stock-level mwh="767305.006981847" mcm="69.4874385954262" cmlng="112308.0" tlng="50538.6" full="25.021909888889%"/><unloaded-inflow mwh="0" mcm="0" cmlng="0.0" tlng="0"/><send-out mwh="56153.9996010373" mcm="5.08532795128363" cmlng="8433.0" tlng="3794.85"/><reloaded mwh="0" mcm="0" cmlng="0.0" tlng="0"/><truck-load mwh="1496.11011370437" mcm="0.135488311313063" cmlng="218.97749999999999" tlng="98.539875"/></lng>