<?xml version="1.0" encoding="utf-8"?>
<lng xmlns="http://energy.icis.com/ns/eu-gas-fundamentals" created-on="2017-10-26T11:10:27Z+1"><country>Spain</country><point>Mugardos</point><lso>Reganosa</lso><gas-quality>H</gas-quality><plant-type>LNG Peak Shaving/LNG Terminal</plant-type><period type="gas-day" from="2017-12-23T23:00:00Z" to="2017-12-24T23:00:00Z"/><acquired>2017-10-26T11:10:27Z+1</acquired><state version="1">Forecast</state><capacity mwh="2049670.34468623" mcm="185.1375825" cmlng="300000.0" tlng="135000.0" country-percentage="9.04568068747173%"/><stock-level mwh="712564.999924457" mcm="64.3628190270384" cmlng="102984.881744082" tlng="46343.1967848369" full="34.7648587379812%"/><unloaded-inflow mwh="0" mcm="0" cmlng="0.0" tlng="0"/><send-out mwh="25757.3168835323" mcm="2.32654357900349" cmlng="3722.6277372262698" tlng="1675.18248175182"/></lng>