<?xml version="1.0" encoding="utf-8"?>
<lng xmlns="http://energy.icis.com/ns/eu-gas-fundamentals" created-on="2016-12-05T06:06:46Z"><country>Belgium</country><point>Zeebrugge</point><lso>Fluxys</lso><gas-quality>H</gas-quality><plant-type>LNG Terminal</plant-type><period type="gas-day" from="2016-12-04T05:00:00Z" to="2016-12-05T05:00:00Z"/><acquired>2016-12-05T06:06:46Z</acquired><state version="2">Provisional</state><capacity mwh="2536783.35870117" mcm="234.5076045" cmlng="380000.0" tlng="171000.0" country-percentage="100%"/><stock-level mwh="244024.29602599" mcm="22.5583130323565" cmlng="36564.3722627307" tlng="16453.9675182288" full="9.61943774934449%"/><unloaded-inflow mwh="0" mcm="0" cmlng="0" tlng="0"/><send-out mwh="21599.8165970076" mcm="1.97881064683245" cmlng="3236.49631500455" tlng="1456.42334175205"/><reloaded mwh="0" mcm="0" cmlng="0" tlng="0"/></lng>