<?xml version="1.0" encoding="utf-8"?>
<lng xmlns="http://energy.icis.com/ns/eu-gas-fundamentals" created-on="2017-09-19T11:10:22Z+1"><country>Spain</country><point>Barcelona</point><lso>Enagas</lso><gas-quality>H</gas-quality><plant-type>LNG Peak Shaving/LNG Terminal</plant-type><period type="gas-day" from="2017-09-27T23:00:00Z+1" to="2017-09-28T23:00:00Z+1"/><acquired>2017-09-19T11:10:22Z+1</acquired><state version="45">Forecast</state><capacity mwh="5192498.20653845" mcm="469.015209" cmlng="760000.0" tlng="342000.0" country-percentage="22.9157244082617%"/><stock-level mwh="2256470.87860486" mcm="203.816952579518" cmlng="326120.96667212498" tlng="146754.435002456" full="43.4563631772371%"/><unloaded-inflow mwh="0" mcm="0" cmlng="0.0" tlng="0"/><send-out mwh="192568.739879099" mcm="17.393875585269" cmlng="27831.382268506499" tlng="12524.1220208279"/></lng>