<?xml version="1.0" encoding="utf-8"?>
<lng xmlns="http://energy.icis.com/ns/eu-gas-fundamentals" created-on="2014-02-17T10:25:15Z"><country>Italy</country><point>Panigaglia</point><lso>GNL Italia</lso><gas-quality>H</gas-quality><plant-type>LNG Terminal</plant-type><period type="gas-day" from="2014-02-14T05:00:00Z" to="2014-02-15T05:00:00Z"/><acquired>2014-02-17T10:25:15Z</acquired><state version="1">Provisional</state><capacity mwh="683880" mcm="61.7125275" cmlng="100000.0" tlng="45000.0" country-percentage="28.5714285714286%"/><stock-level mwh="170215.422098" mcm="15.3600396519081" cmlng="24889.6622357724" tlng="11200.3480060976" full="24.8896622357724%"/><unloaded-inflow mwh="175598.7" mcm="15.8458203233232" cmlng="25676.8292682927" tlng="11554.5731707317"/><send-out mwh="2852.921902" mcm="0.25744431966504" cmlng="417.167032520325" tlng="187.725164634146"/></lng>