<?xml version="1.0" encoding="utf-8"?>
<lng xmlns="http://energy.icis.com/ns/eu-gas-fundamentals" created-on="2016-03-28T10:30:39Z+1"><country>Great Britain</country><point>Milford Haven - Dragon</point><lso>Dragon LNG Ltd</lso><gas-quality>H</gas-quality><plant-type>LNG Terminal</plant-type><period type="gas-day" from="2011-12-29T06:00:00Z" to="2011-12-30T06:00:00Z"/><acquired>2016-03-28T10:30:39Z+1</acquired><state version="1">Provisional</state><capacity mwh="2261995.64565839" mcm="197.480088" cmlng="320000.0" tlng="144000.0" country-percentage="15.2744630071599%"/><stock-level mwh="1769217.064" mcm="154.458803738382" cmlng="250287.59960995201" tlng="112629.419824478" full="78.2148748781102%"/><unloaded-inflow mwh="0" mcm="0" cmlng="0.0" tlng="0.0"/><send-out mwh="5471.165" mcm="0.477651735420579" cmlng="773.99477021999996" tlng="348.29764659900002"/><reloaded mwh="0" mcm="0" cmlng="0.0" tlng="0.0"/></lng>